imageinsightai/__init__.py
imageinsightai/captioner.py
imageinsightai-0.1.0.dist-info/METADATA
imageinsightai-0.1.0.dist-info/WHEEL
imageinsightai-0.1.0.dist-info/top_level.txt
imageinsightai-0.1.0.dist-info/RECORD
